sms_boomber/__init__.py
sms_boomber/__main__.py
sms_boomber-1.4.9.dist-info/LICENSE
sms_boomber-1.4.9.dist-info/METADATA
sms_boomber-1.4.9.dist-info/WHEEL
sms_boomber-1.4.9.dist-info/entry_points.txt
sms_boomber-1.4.9.dist-info/top_level.txt
sms_boomber-1.4.9.dist-info/RECORD
